swiftdeploy/__init__.py
swiftdeploy/app.py
swiftdeploy/model.py
swiftdeploy/settings.py
swiftdeploy/html/__init__.py
swiftdeploy/html/config.py
swiftdeploy/html/htmlcontent.py
swiftdeploy/html/tags.py
swiftdeploy/html/utils.py
swiftdeploy-0.5.1.dist-info/LICENSE
swiftdeploy-0.5.1.dist-info/METADATA
swiftdeploy-0.5.1.dist-info/WHEEL
swiftdeploy-0.5.1.dist-info/top_level.txt
swiftdeploy-0.5.1.dist-info/RECORD
